fastapi_jwt/__init__.py
fastapi_jwt/jwt.py
fastapi_jwt/py.typed
fastapi_jwt_extended-1.0.0.dist-info/LICENSE
fastapi_jwt_extended-1.0.0.dist-info/METADATA
fastapi_jwt_extended-1.0.0.dist-info/WHEEL
fastapi_jwt_extended-1.0.0.dist-info/top_level.txt
fastapi_jwt_extended-1.0.0.dist-info/RECORD
